{"memory":{"totalJSHeapSize":21058022,"usedJSHeapSize":14509534,"jsHeapSizeLimit":2172649472},"resources":[],"referrer":"","eventType":1,"firstPaint":2972.4000000953674,"firstContentfulPaint":2972.4000000953674,"startTime":1768115598962,"versions":{"fl":"2024.11.0","js":"2024.6.1","timings":2},"pageloadId":"d6fd744e-e7e4-4418-9c67-32a2046c3d36","location":"https://practicesoftwaretesting.com/","nt":"navigate","timingsV2":{"unloadEventStart":0,"unloadEventEnd":0,"domInteractive":924.5999999046326,"domContentLoadedEventStart":2868.0999999046326,"domContentLoadedEventEnd":2872.7000002861023,"domComplete":4066.7000002861023,"loadEventStart":4066.800000190735,"loadEventEnd":4070.5,"type":"navigate","redirectCount":0,"criticalCHRestart":0,"activationStart":0,"initiatorType":"navigation","nextHopProtocol":"h3","deliveryType":"","workerStart":0,"redirectStart":0,"redirectEnd":0,"fetchStart":1,"domainLookupStart":2.3000001907348633,"domainLookupEnd":17.59999990463257,"connectStart":17.59999990463257,"connectEnd":44,"secureConnectionStart":18.800000190734863,"requestStart":44.200000286102295,"responseStart":844.2000002861023,"responseEnd":846.2000002861023,"transferSize":3434,"encodedBodySize":3134,"decodedBodySize":7564,"responseStatus":200,"firstInterimResponseStart":0,"renderBlockingStatus":"non-blocking","name":"https://practicesoftwaretesting.com/","entryType":"navigation","startTime":0,"duration":4070.5},"dt":"","siteToken":"df13a0ecec6e47d4a531b7da7efbd6fc","st":2}